[{"pathway_name":"Dopamine Neurotransmitter Release Cycle (R-HSA-212676)","Size":23,"Coverage":0.04,"TDP.bound":1.0,"TDP.estimate":1.0,"SC.adjP":0.0335233947,"Comp.0.99.adjP":0.0335233947,"cancer_type":"colon","group":"without_both","pathway_genes":["APBA1","CASK","CPLX1","LIN7A","LIN7B","LIN7C","PPFIA1","PPFIA2","PPFIA3","PPFIA4","RAB3A","RIMS1","SLC18A2","SNAP25","STX1A","STXBP1","SYN1","SYN2","SYN3","SYT1","TSPOAP1","UNC13B","VAMP2"],"cancer_rank":71.5,"pathway_times_enriched":5,"pathway_avg_rank":323.7,"mean_expr":-1.0,"rank_size":0.013986014,"avg_rank_size":0.0030892802,"avg_rank_label":"323.7"},{"pathway_name":"Dopamine Neurotransmitter Release Cycle (R-HSA-212676)","Size":23,"Coverage":0.04,"TDP.bound":1.0,"TDP.estimate":1.0,"SC.adjP":0.0000000258,"Comp.0.99.adjP":0.0000000258,"cancer_type":"hnscc","group":"without_both","pathway_genes":["APBA1","CASK","CPLX1","LIN7A","LIN7B","LIN7C","PPFIA1","PPFIA2","PPFIA3","PPFIA4","RAB3A","RIMS1","SLC18A2","SNAP25","STX1A","STXBP1","SYN1","SYN2","SYN3","SYT1","TSPOAP1","UNC13B","VAMP2"],"cancer_rank":14.5,"pathway_times_enriched":5,"pathway_avg_rank":323.7,"mean_expr":-0.6,"rank_size":0.0689655172,"avg_rank_size":0.0030892802,"avg_rank_label":"323.7"},{"pathway_name":"Dopamine Neurotransmitter Release Cycle (R-HSA-212676)","Size":23,"Coverage":0.04,"TDP.bound":1.0,"TDP.estimate":1.0,"SC.adjP":0.0078638602,"Comp.0.99.adjP":0.0078638602,"cancer_type":"lscc","group":"without_both","pathway_genes":["APBA1","CASK","CPLX1","LIN7A","LIN7B","LIN7C","PPFIA1","PPFIA2","PPFIA3","PPFIA4","RAB3A","RIMS1","SLC18A2","SNAP25","STX1A","STXBP1","SYN1","SYN2","SYN3","SYT1","TSPOAP1","UNC13B","VAMP2"],"cancer_rank":20.5,"pathway_times_enriched":5,"pathway_avg_rank":323.7,"mean_expr":-0.5,"rank_size":0.0487804878,"avg_rank_size":0.0030892802,"avg_rank_label":"323.7"},{"pathway_name":"Dopamine Neurotransmitter Release Cycle (R-HSA-212676)","Size":23,"Coverage":0.13,"TDP.bound":1.0,"TDP.estimate":1.0,"SC.adjP":0.0131054044,"Comp.0.99.adjP":0.0499734375,"cancer_type":"luad","group":"without_both","pathway_genes":["APBA1","CASK","CPLX1","LIN7A","LIN7B","LIN7C","PPFIA1","PPFIA2","PPFIA3","PPFIA4","RAB3A","RIMS1","SLC18A2","SNAP25","STX1A","STXBP1","SYN1","SYN2","SYN3","SYT1","TSPOAP1","UNC13B","VAMP2"],"cancer_rank":835.0,"pathway_times_enriched":5,"pathway_avg_rank":323.7,"mean_expr":-0.3333333333,"rank_size":0.0011976048,"avg_rank_size":0.0030892802,"avg_rank_label":"323.7"},{"pathway_name":"Dopamine Neurotransmitter Release Cycle (R-HSA-212676)","Size":23,"Coverage":0.17,"TDP.bound":1.0,"TDP.estimate":1.0,"SC.adjP":0.0499147504,"Comp.0.99.adjP":0.0499147504,"cancer_type":"ovarian","group":"without_both","pathway_genes":["APBA1","CASK","CPLX1","LIN7A","LIN7B","LIN7C","PPFIA1","PPFIA2","PPFIA3","PPFIA4","RAB3A","RIMS1","SLC18A2","SNAP25","STX1A","STXBP1","SYN1","SYN2","SYN3","SYT1","TSPOAP1","UNC13B","VAMP2"],"cancer_rank":677.0,"pathway_times_enriched":5,"pathway_avg_rank":323.7,"mean_expr":-0.5555555556,"rank_size":0.0014771049,"avg_rank_size":0.0030892802,"avg_rank_label":"323.7"},{"pathway_name":"E2F-enabled inhibition of pre-replication complex formation (R-HSA-113507)","Size":9,"Coverage":0.11,"TDP.bound":1.0,"TDP.estimate":1.0,"SC.adjP":0.0498921085,"Comp.0.99.adjP":0.0498921085,"cancer_type":"colon","group":"without_both","pathway_genes":["CCNB1","CDK1","MCM8","ORC1","ORC2","ORC3","ORC4","ORC5","ORC6"],"cancer_rank":881.0,"pathway_times_enriched":5,"pathway_avg_rank":359.3,"mean_expr":1.0,"rank_size":0.0011350738,"avg_rank_size":0.0027831895,"avg_rank_label":"359.3"},{"pathway_name":"E2F-enabled inhibition of pre-replication complex formation (R-HSA-113507)","Size":9,"Coverage":0.33,"TDP.bound":1.0,"TDP.estimate":1.0,"SC.adjP":0.0000000006,"Comp.0.99.adjP":0.0377019043,"cancer_type":"hnscc","group":"without_both","pathway_genes":["CCNB1","CDK1","MCM8","ORC1","ORC2","ORC3","ORC4","ORC5","ORC6"],"cancer_rank":104.0,"pathway_times_enriched":5,"pathway_avg_rank":359.3,"mean_expr":0.7142857143,"rank_size":0.0096153846,"avg_rank_size":0.0027831895,"avg_rank_label":"359.3"},{"pathway_name":"E2F-enabled inhibition of pre-replication complex formation (R-HSA-113507)","Size":9,"Coverage":0.11,"TDP.bound":1.0,"TDP.estimate":1.0,"SC.adjP":0.0497956271,"Comp.0.99.adjP":0.0497956271,"cancer_type":"lscc","group":"without_both","pathway_genes":["CCNB1","CDK1","MCM8","ORC1","ORC2","ORC3","ORC4","ORC5","ORC6"],"cancer_rank":676.5,"pathway_times_enriched":5,"pathway_avg_rank":359.3,"mean_expr":1.0,"rank_size":0.0014781966,"avg_rank_size":0.0027831895,"avg_rank_label":"359.3"},{"pathway_name":"E2F-enabled inhibition of pre-replication complex formation (R-HSA-113507)","Size":9,"Coverage":0.33,"TDP.bound":1.0,"TDP.estimate":1.0,"SC.adjP":0.0040017784,"Comp.0.99.adjP":0.0231882657,"cancer_type":"luad","group":"without_both","pathway_genes":["CCNB1","CDK1","MCM8","ORC1","ORC2","ORC3","ORC4","ORC5","ORC6"],"cancer_rank":125.0,"pathway_times_enriched":5,"pathway_avg_rank":359.3,"mean_expr":1.0,"rank_size":0.008,"avg_rank_size":0.0027831895,"avg_rank_label":"359.3"},{"pathway_name":"E2F-enabled inhibition of pre-replication complex formation (R-HSA-113507)","Size":9,"Coverage":0.11,"TDP.bound":1.0,"TDP.estimate":1.0,"SC.adjP":0.0302881787,"Comp.0.99.adjP":0.0302881787,"cancer_type":"ovarian","group":"without_both","pathway_genes":["CCNB1","CDK1","MCM8","ORC1","ORC2","ORC3","ORC4","ORC5","ORC6"],"cancer_rank":10.0,"pathway_times_enriched":5,"pathway_avg_rank":359.3,"mean_expr":1.0,"rank_size":0.1,"avg_rank_size":0.0027831895,"avg_rank_label":"359.3"},{"pathway_name":"TP53 regulates transcription of additional cell cycle genes whose exact role in the p53 pathway remain uncertain (R-HSA-6804115)","Size":21,"Coverage":0.1,"TDP.bound":1.0,"TDP.estimate":1.0,"SC.adjP":0.0498921085,"Comp.0.99.adjP":0.0498921085,"cancer_type":"colon","group":"without_both","pathway_genes":["BTG2","CDC25C","CENPJ","CNOT1","CNOT10","CNOT11","CNOT2","CNOT3","CNOT4","CNOT6","CNOT6L","CNOT7","CNOT8","NPM1","PLAGL1","PLK2","PLK3","RGCC","RQCD1","TNKS1BP1","TP53"],"cancer_rank":881.0,"pathway_times_enriched":5,"pathway_avg_rank":468.2,"mean_expr":0.3333333333,"rank_size":0.0011350738,"avg_rank_size":0.0021358394,"avg_rank_label":"468.2"},{"pathway_name":"TP53 regulates transcription of additional cell cycle genes whose exact role in the p53 pathway remain uncertain (R-HSA-6804115)","Size":21,"Coverage":0.05,"TDP.bound":1.0,"TDP.estimate":1.0,"SC.adjP":0.000726638,"Comp.0.99.adjP":0.000726638,"cancer_type":"hnscc","group":"without_both","pathway_genes":["BTG2","CDC25C","CENPJ","CNOT1","CNOT10","CNOT11","CNOT2","CNOT3","CNOT4","CNOT6","CNOT6L","CNOT7","CNOT8","NPM1","PLAGL1","PLK2","PLK3","RGCC","RQCD1","TNKS1BP1","TP53"],"cancer_rank":44.0,"pathway_times_enriched":5,"pathway_avg_rank":468.2,"mean_expr":1.0,"rank_size":0.0227272727,"avg_rank_size":0.0021358394,"avg_rank_label":"468.2"},{"pathway_name":"TP53 regulates transcription of additional cell cycle genes whose exact role in the p53 pathway remain uncertain (R-HSA-6804115)","Size":21,"Coverage":0.14,"TDP.bound":1.0,"TDP.estimate":1.0,"SC.adjP":0.0497956271,"Comp.0.99.adjP":0.0497956271,"cancer_type":"lscc","group":"without_both","pathway_genes":["BTG2","CDC25C","CENPJ","CNOT1","CNOT10","CNOT11","CNOT2","CNOT3","CNOT4","CNOT6","CNOT6L","CNOT7","CNOT8","NPM1","PLAGL1","PLK2","PLK3","RGCC","RQCD1","TNKS1BP1","TP53"],"cancer_rank":676.5,"pathway_times_enriched":5,"pathway_avg_rank":468.2,"mean_expr":0.6666666667,"rank_size":0.0014781966,"avg_rank_size":0.0021358394,"avg_rank_label":"468.2"},{"pathway_name":"TP53 regulates transcription of additional cell cycle genes whose exact role in the p53 pathway remain uncertain (R-HSA-6804115)","Size":21,"Coverage":0.1,"TDP.bound":1.0,"TDP.estimate":1.0,"SC.adjP":0.0002177875,"Comp.0.99.adjP":0.0006721287,"cancer_type":"luad","group":"without_both","pathway_genes":["BTG2","CDC25C","CENPJ","CNOT1","CNOT10","CNOT11","CNOT2","CNOT3","CNOT4","CNOT6","CNOT6L","CNOT7","CNOT8","NPM1","PLAGL1","PLK2","PLK3","RGCC","RQCD1","TNKS1BP1","TP53"],"cancer_rank":62.5,"pathway_times_enriched":5,"pathway_avg_rank":468.2,"mean_expr":0.5555555556,"rank_size":0.016,"avg_rank_size":0.0021358394,"avg_rank_label":"468.2"},{"pathway_name":"TP53 regulates transcription of additional cell cycle genes whose exact role in the p53 pathway remain uncertain (R-HSA-6804115)","Size":21,"Coverage":0.14,"TDP.bound":1.0,"TDP.estimate":1.0,"SC.adjP":0.0499147504,"Comp.0.99.adjP":0.0499147504,"cancer_type":"ovarian","group":"without_both","pathway_genes":["BTG2","CDC25C","CENPJ","CNOT1","CNOT10","CNOT11","CNOT2","CNOT3","CNOT4","CNOT6","CNOT6L","CNOT7","CNOT8","NPM1","PLAGL1","PLK2","PLK3","RGCC","RQCD1","TNKS1BP1","TP53"],"cancer_rank":677.0,"pathway_times_enriched":5,"pathway_avg_rank":468.2,"mean_expr":1.0,"rank_size":0.0014771049,"avg_rank_size":0.0021358394,"avg_rank_label":"468.2"},{"pathway_name":"DARPP-32 events (R-HSA-180024)","Size":24,"Coverage":0.04,"TDP.bound":1.0,"TDP.estimate":1.0,"SC.adjP":0.0496925382,"Comp.0.99.adjP":0.0496925382,"cancer_type":"colon","group":"without_both","pathway_genes":["CALM1","CDK5","PDE4A","PDE4B","PDE4C","PDE4D","PPP1CA","PPP1R1B","PPP2CA","PPP2CB","PPP2R1A","PPP2R1B","PPP2R5D","PPP3CA","PPP3CB","PPP3CC","PPP3R1","PRKACA","PRKACB","PRKACG","PRKAR1A","PRKAR1B","PRKAR2A","PRKAR2B"],"cancer_rank":135.0,"pathway_times_enriched":5,"pathway_avg_rank":473.9,"mean_expr":-0.625,"rank_size":0.0074074074,"avg_rank_size":0.0021101498,"avg_rank_label":"473.9"},{"pathway_name":"DARPP-32 events (R-HSA-180024)","Size":24,"Coverage":0.04,"TDP.bound":1.0,"TDP.estimate":1.0,"SC.adjP":0.0011422765,"Comp.0.99.adjP":0.0011422765,"cancer_type":"hnscc","group":"without_both","pathway_genes":["CALM1","CDK5","PDE4A","PDE4B","PDE4C","PDE4D","PPP1CA","PPP1R1B","PPP2CA","PPP2CB","PPP2R1A","PPP2R1B","PPP2R5D","PPP3CA","PPP3CB","PPP3CC","PPP3R1","PRKACA","PRKACB","PRKACG","PRKAR1A","PRKAR1B","PRKAR2A","PRKAR2B"],"cancer_rank":46.0,"pathway_times_enriched":5,"pathway_avg_rank":473.9,"mean_expr":-0.7647058824,"rank_size":0.0217391304,"avg_rank_size":0.0021101498,"avg_rank_label":"473.9"},{"pathway_name":"DARPP-32 events (R-HSA-180024)","Size":24,"Coverage":0.04,"TDP.bound":1.0,"TDP.estimate":1.0,"SC.adjP":0.0497956271,"Comp.0.99.adjP":0.0497956271,"cancer_type":"lscc","group":"without_both","pathway_genes":["CALM1","CDK5","PDE4A","PDE4B","PDE4C","PDE4D","PPP1CA","PPP1R1B","PPP2CA","PPP2CB","PPP2R1A","PPP2R1B","PPP2R5D","PPP3CA","PPP3CB","PPP3CC","PPP3R1","PRKACA","PRKACB","PRKACG","PRKAR1A","PRKAR1B","PRKAR2A","PRKAR2B"],"cancer_rank":676.5,"pathway_times_enriched":5,"pathway_avg_rank":473.9,"mean_expr":-0.7777777778,"rank_size":0.0014781966,"avg_rank_size":0.0021101498,"avg_rank_label":"473.9"},{"pathway_name":"DARPP-32 events (R-HSA-180024)","Size":24,"Coverage":0.17,"TDP.bound":1.0,"TDP.estimate":1.0,"SC.adjP":0.00000366,"Comp.0.99.adjP":0.0499734375,"cancer_type":"luad","group":"without_both","pathway_genes":["CALM1","CDK5","PDE4A","PDE4B","PDE4C","PDE4D","PPP1CA","PPP1R1B","PPP2CA","PPP2CB","PPP2R1A","PPP2R1B","PPP2R5D","PPP3CA","PPP3CB","PPP3CC","PPP3R1","PRKACA","PRKACB","PRKACG","PRKAR1A","PRKAR1B","PRKAR2A","PRKAR2B"],"cancer_rank":835.0,"pathway_times_enriched":5,"pathway_avg_rank":473.9,"mean_expr":-0.5555555556,"rank_size":0.0011976048,"avg_rank_size":0.0021101498,"avg_rank_label":"473.9"},{"pathway_name":"DARPP-32 events (R-HSA-180024)","Size":24,"Coverage":0.12,"TDP.bound":1.0,"TDP.estimate":1.0,"SC.adjP":0.0499147504,"Comp.0.99.adjP":0.0499147504,"cancer_type":"ovarian","group":"without_both","pathway_genes":["CALM1","CDK5","PDE4A","PDE4B","PDE4C","PDE4D","PPP1CA","PPP1R1B","PPP2CA","PPP2CB","PPP2R1A","PPP2R1B","PPP2R5D","PPP3CA","PPP3CB","PPP3CC","PPP3R1","PRKACA","PRKACB","PRKACG","PRKAR1A","PRKAR1B","PRKAR2A","PRKAR2B"],"cancer_rank":677.0,"pathway_times_enriched":5,"pathway_avg_rank":473.9,"mean_expr":-0.75,"rank_size":0.0014771049,"avg_rank_size":0.0021101498,"avg_rank_label":"473.9"},{"pathway_name":"Interleukin-27 signaling (R-HSA-9020956)","Size":11,"Coverage":0.09,"TDP.bound":1.0,"TDP.estimate":1.0,"SC.adjP":0.0498921085,"Comp.0.99.adjP":0.0498921085,"cancer_type":"colon","group":"without_both","pathway_genes":["CANX","CRLF1","EBI3","IL27","IL27RA","IL6ST","JAK1","JAK2","STAT1","STAT3","TYK2"],"cancer_rank":881.0,"pathway_times_enriched":5,"pathway_avg_rank":483.9,"mean_expr":-0.2,"rank_size":0.0011350738,"avg_rank_size":0.0020665427,"avg_rank_label":"483.9"},{"pathway_name":"Interleukin-27 signaling (R-HSA-9020956)","Size":11,"Coverage":0.09,"TDP.bound":1.0,"TDP.estimate":1.0,"SC.adjP":0.0000050332,"Comp.0.99.adjP":0.0000050332,"cancer_type":"hnscc","group":"without_both","pathway_genes":["CANX","CRLF1","EBI3","IL27","IL27RA","IL6ST","JAK1","JAK2","STAT1","STAT3","TYK2"],"cancer_rank":22.0,"pathway_times_enriched":5,"pathway_avg_rank":483.9,"mean_expr":0.2,"rank_size":0.0454545455,"avg_rank_size":0.0020665427,"avg_rank_label":"483.9"},{"pathway_name":"Interleukin-27 signaling (R-HSA-9020956)","Size":11,"Coverage":0.18,"TDP.bound":1.0,"TDP.estimate":1.0,"SC.adjP":0.0497956271,"Comp.0.99.adjP":0.0497956271,"cancer_type":"lscc","group":"without_both","pathway_genes":["CANX","CRLF1","EBI3","IL27","IL27RA","IL6ST","JAK1","JAK2","STAT1","STAT3","TYK2"],"cancer_rank":676.5,"pathway_times_enriched":5,"pathway_avg_rank":483.9,"mean_expr":0.0,"rank_size":0.0014781966,"avg_rank_size":0.0020665427,"avg_rank_label":"483.9"},{"pathway_name":"Interleukin-27 signaling (R-HSA-9020956)","Size":11,"Coverage":0.18,"TDP.bound":1.0,"TDP.estimate":1.0,"SC.adjP":0.0499734375,"Comp.0.99.adjP":0.0499734375,"cancer_type":"luad","group":"without_both","pathway_genes":["CANX","CRLF1","EBI3","IL27","IL27RA","IL6ST","JAK1","JAK2","STAT1","STAT3","TYK2"],"cancer_rank":835.0,"pathway_times_enriched":5,"pathway_avg_rank":483.9,"mean_expr":0.1111111111,"rank_size":0.0011976048,"avg_rank_size":0.0020665427,"avg_rank_label":"483.9"},{"pathway_name":"Interleukin-27 signaling (R-HSA-9020956)","Size":11,"Coverage":0.09,"TDP.bound":1.0,"TDP.estimate":1.0,"SC.adjP":0.005724026,"Comp.0.99.adjP":0.005724026,"cancer_type":"ovarian","group":"without_both","pathway_genes":["CANX","CRLF1","EBI3","IL27","IL27RA","IL6ST","JAK1","JAK2","STAT1","STAT3","TYK2"],"cancer_rank":5.0,"pathway_times_enriched":5,"pathway_avg_rank":483.9,"mean_expr":0.0,"rank_size":0.2,"avg_rank_size":0.0020665427,"avg_rank_label":"483.9"},{"pathway_name":"Defensins (R-HSA-1461973)","Size":49,"Coverage":0.06,"TDP.bound":1.0,"TDP.estimate":1.0,"SC.adjP":0.0048697283,"Comp.0.99.adjP":0.0498921085,"cancer_type":"colon","group":"without_both","pathway_genes":["ART1","CCR2","CCR6","CD4","DEFA1","DEFA3","DEFA4","DEFA5","DEFA6","DEFB1","DEFB103A","DEFB104A","DEFB105A","DEFB106A","DEFB107A","DEFB108B","DEFB108P1","DEFB109B","DEFB110","DEFB112","DEFB113","DEFB114","DEFB115","DEFB116","DEFB117","DEFB118","DEFB119","DEFB121","DEFB123","DEFB124","DEFB125","DEFB126","DEFB127","DEFB128","DEFB129","DEFB130A","DEFB130B","DEFB131","DEFB132","DEFB133","DEFB134","DEFB135","DEFB136","DEFB4A","PRSS2","PRSS3","TLR1","TLR2","env"],"cancer_rank":881.0,"pathway_times_enriched":5,"pathway_avg_rank":484.2,"mean_expr":0.0,"rank_size":0.0011350738,"avg_rank_size":0.0020652623,"avg_rank_label":"484.2"},{"pathway_name":"Defensins (R-HSA-1461973)","Size":49,"Coverage":0.04,"TDP.bound":1.0,"TDP.estimate":1.0,"SC.adjP":0.0459971035,"Comp.0.99.adjP":0.0499794894,"cancer_type":"hnscc","group":"without_both","pathway_genes":["ART1","CCR2","CCR6","CD4","DEFA1","DEFA3","DEFA4","DEFA5","DEFA6","DEFB1","DEFB103A","DEFB104A","DEFB105A","DEFB106A","DEFB107A","DEFB108B","DEFB108P1","DEFB109B","DEFB110","DEFB112","DEFB113","DEFB114","DEFB115","DEFB116","DEFB117","DEFB118","DEFB119","DEFB121","DEFB123","DEFB124","DEFB125","DEFB126","DEFB127","DEFB128","DEFB129","DEFB130A","DEFB130B","DEFB131","DEFB132","DEFB133","DEFB134","DEFB135","DEFB136","DEFB4A","PRSS2","PRSS3","TLR1","TLR2","env"],"cancer_rank":131.0,"pathway_times_enriched":5,"pathway_avg_rank":484.2,"mean_expr":0.7142857143,"rank_size":0.0076335878,"avg_rank_size":0.0020652623,"avg_rank_label":"484.2"},{"pathway_name":"Defensins (R-HSA-1461973)","Size":49,"Coverage":0.02,"TDP.bound":1.0,"TDP.estimate":1.0,"SC.adjP":0.0497956271,"Comp.0.99.adjP":0.0497956271,"cancer_type":"lscc","group":"without_both","pathway_genes":["ART1","CCR2","CCR6","CD4","DEFA1","DEFA3","DEFA4","DEFA5","DEFA6","DEFB1","DEFB103A","DEFB104A","DEFB105A","DEFB106A","DEFB107A","DEFB108B","DEFB108P1","DEFB109B","DEFB110","DEFB112","DEFB113","DEFB114","DEFB115","DEFB116","DEFB117","DEFB118","DEFB119","DEFB121","DEFB123","DEFB124","DEFB125","DEFB126","DEFB127","DEFB128","DEFB129","DEFB130A","DEFB130B","DEFB131","DEFB132","DEFB133","DEFB134","DEFB135","DEFB136","DEFB4A","PRSS2","PRSS3","TLR1","TLR2","env"],"cancer_rank":676.5,"pathway_times_enriched":5,"pathway_avg_rank":484.2,"mean_expr":-0.5,"rank_size":0.0014781966,"avg_rank_size":0.0020652623,"avg_rank_label":"484.2"},{"pathway_name":"Defensins (R-HSA-1461973)","Size":49,"Coverage":0.02,"TDP.bound":1.0,"TDP.estimate":1.0,"SC.adjP":0.0004826087,"Comp.0.99.adjP":0.0004826087,"cancer_type":"luad","group":"without_both","pathway_genes":["ART1","CCR2","CCR6","CD4","DEFA1","DEFA3","DEFA4","DEFA5","DEFA6","DEFB1","DEFB103A","DEFB104A","DEFB105A","DEFB106A","DEFB107A","DEFB108B","DEFB108P1","DEFB109B","DEFB110","DEFB112","DEFB113","DEFB114","DEFB115","DEFB116","DEFB117","DEFB118","DEFB119","DEFB121","DEFB123","DEFB124","DEFB125","DEFB126","DEFB127","DEFB128","DEFB129","DEFB130A","DEFB130B","DEFB131","DEFB132","DEFB133","DEFB134","DEFB135","DEFB136","DEFB4A","PRSS2","PRSS3","TLR1","TLR2","env"],"cancer_rank":55.5,"pathway_times_enriched":5,"pathway_avg_rank":484.2,"mean_expr":-0.5,"rank_size":0.018018018,"avg_rank_size":0.0020652623,"avg_rank_label":"484.2"},{"pathway_name":"Defensins (R-HSA-1461973)","Size":49,"Coverage":0.02,"TDP.bound":1.0,"TDP.estimate":1.0,"SC.adjP":0.0499147504,"Comp.0.99.adjP":0.0499147504,"cancer_type":"ovarian","group":"without_both","pathway_genes":["ART1","CCR2","CCR6","CD4","DEFA1","DEFA3","DEFA4","DEFA5","DEFA6","DEFB1","DEFB103A","DEFB104A","DEFB105A","DEFB106A","DEFB107A","DEFB108B","DEFB108P1","DEFB109B","DEFB110","DEFB112","DEFB113","DEFB114","DEFB115","DEFB116","DEFB117","DEFB118","DEFB119","DEFB121","DEFB123","DEFB124","DEFB125","DEFB126","DEFB127","DEFB128","DEFB129","DEFB130A","DEFB130B","DEFB131","DEFB132","DEFB133","DEFB134","DEFB135","DEFB136","DEFB4A","PRSS2","PRSS3","TLR1","TLR2","env"],"cancer_rank":677.0,"pathway_times_enriched":5,"pathway_avg_rank":484.2,"mean_expr":-1.0,"rank_size":0.0014771049,"avg_rank_size":0.0020652623,"avg_rank_label":"484.2"},{"pathway_name":"PI3K\/AKT activation (R-HSA-198203)","Size":9,"Coverage":0.11,"TDP.bound":1.0,"TDP.estimate":1.0,"SC.adjP":0.0029876295,"Comp.0.99.adjP":0.0029876295,"cancer_type":"colon","group":"without_both","pathway_genes":["IRS1","IRS2","NGF","NTRK1","PIK3CA","PIK3CB","PIK3R1","PIK3R2","RHOA"],"cancer_rank":32.5,"pathway_times_enriched":5,"pathway_avg_rank":488.9,"mean_expr":-1.0,"rank_size":0.0307692308,"avg_rank_size":0.0020454081,"avg_rank_label":"488.9"},{"pathway_name":"PI3K\/AKT activation (R-HSA-198203)","Size":9,"Coverage":0.11,"TDP.bound":1.0,"TDP.estimate":1.0,"SC.adjP":0.0499794894,"Comp.0.99.adjP":0.0499794894,"cancer_type":"hnscc","group":"without_both","pathway_genes":["IRS1","IRS2","NGF","NTRK1","PIK3CA","PIK3CB","PIK3R1","PIK3R2","RHOA"],"cancer_rank":868.5,"pathway_times_enriched":5,"pathway_avg_rank":488.9,"mean_expr":0.6,"rank_size":0.0011514105,"avg_rank_size":0.0020454081,"avg_rank_label":"488.9"},{"pathway_name":"PI3K\/AKT activation (R-HSA-198203)","Size":9,"Coverage":0.11,"TDP.bound":1.0,"TDP.estimate":1.0,"SC.adjP":0.0213021891,"Comp.0.99.adjP":0.0213021891,"cancer_type":"lscc","group":"without_both","pathway_genes":["IRS1","IRS2","NGF","NTRK1","PIK3CA","PIK3CB","PIK3R1","PIK3R2","RHOA"],"cancer_rank":31.5,"pathway_times_enriched":5,"pathway_avg_rank":488.9,"mean_expr":-0.5,"rank_size":0.0317460317,"avg_rank_size":0.0020454081,"avg_rank_label":"488.9"},{"pathway_name":"PI3K\/AKT activation (R-HSA-198203)","Size":9,"Coverage":0.33,"TDP.bound":1.0,"TDP.estimate":1.0,"SC.adjP":0.0000948097,"Comp.0.99.adjP":0.0499734375,"cancer_type":"luad","group":"without_both","pathway_genes":["IRS1","IRS2","NGF","NTRK1","PIK3CA","PIK3CB","PIK3R1","PIK3R2","RHOA"],"cancer_rank":835.0,"pathway_times_enriched":5,"pathway_avg_rank":488.9,"mean_expr":-0.7142857143,"rank_size":0.0011976048,"avg_rank_size":0.0020454081,"avg_rank_label":"488.9"},{"pathway_name":"PI3K\/AKT activation (R-HSA-198203)","Size":9,"Coverage":0.11,"TDP.bound":1.0,"TDP.estimate":1.0,"SC.adjP":0.0499147504,"Comp.0.99.adjP":0.0499147504,"cancer_type":"ovarian","group":"without_both","pathway_genes":["IRS1","IRS2","NGF","NTRK1","PIK3CA","PIK3CB","PIK3R1","PIK3R2","RHOA"],"cancer_rank":677.0,"pathway_times_enriched":5,"pathway_avg_rank":488.9,"mean_expr":-0.3333333333,"rank_size":0.0014771049,"avg_rank_size":0.0020454081,"avg_rank_label":"488.9"},{"pathway_name":"DAG and IP3 signaling (R-HSA-1489509)","Size":41,"Coverage":0.02,"TDP.bound":1.0,"TDP.estimate":1.0,"SC.adjP":0.0496093429,"Comp.0.99.adjP":0.0496093429,"cancer_type":"colon","group":"without_both","pathway_genes":["ADCY1","ADCY2","ADCY3","ADCY4","ADCY5","ADCY6","ADCY7","ADCY8","ADCY9","AHCYL1","CALM1","CAMK2A","CAMK2B","CAMK2D","CAMK2G","CAMK4","CAMKK1","CAMKK2","CREB1","GRK2","ITPR1","ITPR2","ITPR3","KPNA2","NBEA","PDE1A","PDE1B","PDE1C","PLCG1","PRKACA","PRKACB","PRKACG","PRKAR1A","PRKAR1B","PRKAR2A","PRKAR2B","PRKCA","PRKCD","PRKCE","PRKCG","PRKX"],"cancer_rank":116.5,"pathway_times_enriched":5,"pathway_avg_rank":489.1,"mean_expr":-0.6842105263,"rank_size":0.008583691,"avg_rank_size":0.0020445717,"avg_rank_label":"489.1"},{"pathway_name":"DAG and IP3 signaling (R-HSA-1489509)","Size":41,"Coverage":0.12,"TDP.bound":1.0,"TDP.estimate":1.0,"SC.adjP":0.0499794894,"Comp.0.99.adjP":0.0499794894,"cancer_type":"hnscc","group":"without_both","pathway_genes":["ADCY1","ADCY2","ADCY3","ADCY4","ADCY5","ADCY6","ADCY7","ADCY8","ADCY9","AHCYL1","CALM1","CAMK2A","CAMK2B","CAMK2D","CAMK2G","CAMK4","CAMKK1","CAMKK2","CREB1","GRK2","ITPR1","ITPR2","ITPR3","KPNA2","NBEA","PDE1A","PDE1B","PDE1C","PLCG1","PRKACA","PRKACB","PRKACG","PRKAR1A","PRKAR1B","PRKAR2A","PRKAR2B","PRKCA","PRKCD","PRKCE","PRKCG","PRKX"],"cancer_rank":868.5,"pathway_times_enriched":5,"pathway_avg_rank":489.1,"mean_expr":-0.3913043478,"rank_size":0.0011514105,"avg_rank_size":0.0020445717,"avg_rank_label":"489.1"},{"pathway_name":"DAG and IP3 signaling (R-HSA-1489509)","Size":41,"Coverage":0.02,"TDP.bound":1.0,"TDP.estimate":1.0,"SC.adjP":0.0497956271,"Comp.0.99.adjP":0.0497956271,"cancer_type":"lscc","group":"without_both","pathway_genes":["ADCY1","ADCY2","ADCY3","ADCY4","ADCY5","ADCY6","ADCY7","ADCY8","ADCY9","AHCYL1","CALM1","CAMK2A","CAMK2B","CAMK2D","CAMK2G","CAMK4","CAMKK1","CAMKK2","CREB1","GRK2","ITPR1","ITPR2","ITPR3","KPNA2","NBEA","PDE1A","PDE1B","PDE1C","PLCG1","PRKACA","PRKACB","PRKACG","PRKAR1A","PRKAR1B","PRKAR2A","PRKAR2B","PRKCA","PRKCD","PRKCE","PRKCG","PRKX"],"cancer_rank":676.5,"pathway_times_enriched":5,"pathway_avg_rank":489.1,"mean_expr":-0.8125,"rank_size":0.0014781966,"avg_rank_size":0.0020445717,"avg_rank_label":"489.1"},{"pathway_name":"DAG and IP3 signaling (R-HSA-1489509)","Size":41,"Coverage":0.07,"TDP.bound":1.0,"TDP.estimate":1.0,"SC.adjP":0.00000366,"Comp.0.99.adjP":0.0147293058,"cancer_type":"luad","group":"without_both","pathway_genes":["ADCY1","ADCY2","ADCY3","ADCY4","ADCY5","ADCY6","ADCY7","ADCY8","ADCY9","AHCYL1","CALM1","CAMK2A","CAMK2B","CAMK2D","CAMK2G","CAMK4","CAMKK1","CAMKK2","CREB1","GRK2","ITPR1","ITPR2","ITPR3","KPNA2","NBEA","PDE1A","PDE1B","PDE1C","PLCG1","PRKACA","PRKACB","PRKACG","PRKAR1A","PRKAR1B","PRKAR2A","PRKAR2B","PRKCA","PRKCD","PRKCE","PRKCG","PRKX"],"cancer_rank":107.0,"pathway_times_enriched":5,"pathway_avg_rank":489.1,"mean_expr":-0.7692307692,"rank_size":0.0093457944,"avg_rank_size":0.0020445717,"avg_rank_label":"489.1"},{"pathway_name":"DAG and IP3 signaling (R-HSA-1489509)","Size":41,"Coverage":0.07,"TDP.bound":1.0,"TDP.estimate":1.0,"SC.adjP":0.0499147504,"Comp.0.99.adjP":0.0499147504,"cancer_type":"ovarian","group":"without_both","pathway_genes":["ADCY1","ADCY2","ADCY3","ADCY4","ADCY5","ADCY6","ADCY7","ADCY8","ADCY9","AHCYL1","CALM1","CAMK2A","CAMK2B","CAMK2D","CAMK2G","CAMK4","CAMKK1","CAMKK2","CREB1","GRK2","ITPR1","ITPR2","ITPR3","KPNA2","NBEA","PDE1A","PDE1B","PDE1C","PLCG1","PRKACA","PRKACB","PRKACG","PRKAR1A","PRKAR1B","PRKAR2A","PRKAR2B","PRKCA","PRKCD","PRKCE","PRKCG","PRKX"],"cancer_rank":677.0,"pathway_times_enriched":5,"pathway_avg_rank":489.1,"mean_expr":-0.7777777778,"rank_size":0.0014771049,"avg_rank_size":0.0020445717,"avg_rank_label":"489.1"},{"pathway_name":"Neurotransmitter release cycle (R-HSA-112310)","Size":51,"Coverage":0.06,"TDP.bound":1.0,"TDP.estimate":1.0,"SC.adjP":0.0335233947,"Comp.0.99.adjP":0.0498921085,"cancer_type":"colon","group":"without_both","pathway_genes":["ABAT","ALDH5A1","APBA1","ARL6IP5","CASK","CHAT","CPLX1","DNAJC5","GAD1","GAD2","GLS","GLS2","HSPA8","LIN7A","LIN7B","LIN7C","MAOA","NAAA","PPFIA1","PPFIA2","PPFIA3","PPFIA4","RAB3A","RIMS1","SLC17A7","SLC18A2","SLC18A3","SLC1A1","SLC1A2","SLC1A3","SLC1A6","SLC1A7","SLC22A1","SLC22A2","SLC32A1","SLC38A2","SLC5A7","SLC6A1","SLC6A11","SLC6A12","SLC6A13","SNAP25","STX1A","STXBP1","SYN1","SYN2","SYN3","SYT1","TSPOAP1","UNC13B","VAMP2"],"cancer_rank":245.5,"pathway_times_enriched":5,"pathway_avg_rank":489.7,"mean_expr":-0.625,"rank_size":0.0040733198,"avg_rank_size":0.0020420666,"avg_rank_label":"489.7"},{"pathway_name":"Neurotransmitter release cycle (R-HSA-112310)","Size":51,"Coverage":0.02,"TDP.bound":1.0,"TDP.estimate":1.0,"SC.adjP":0.0000000258,"Comp.0.99.adjP":0.0000000258,"cancer_type":"hnscc","group":"without_both","pathway_genes":["ABAT","ALDH5A1","APBA1","ARL6IP5","CASK","CHAT","CPLX1","DNAJC5","GAD1","GAD2","GLS","GLS2","HSPA8","LIN7A","LIN7B","LIN7C","MAOA","NAAA","PPFIA1","PPFIA2","PPFIA3","PPFIA4","RAB3A","RIMS1","SLC17A7","SLC18A2","SLC18A3","SLC1A1","SLC1A2","SLC1A3","SLC1A6","SLC1A7","SLC22A1","SLC22A2","SLC32A1","SLC38A2","SLC5A7","SLC6A1","SLC6A11","SLC6A12","SLC6A13","SNAP25","STX1A","STXBP1","SYN1","SYN2","SYN3","SYT1","TSPOAP1","UNC13B","VAMP2"],"cancer_rank":14.5,"pathway_times_enriched":5,"pathway_avg_rank":489.7,"mean_expr":-0.4444444444,"rank_size":0.0689655172,"avg_rank_size":0.0020420666,"avg_rank_label":"489.7"},{"pathway_name":"Neurotransmitter release cycle (R-HSA-112310)","Size":51,"Coverage":0.04,"TDP.bound":1.0,"TDP.estimate":1.0,"SC.adjP":0.0078638602,"Comp.0.99.adjP":0.0497956271,"cancer_type":"lscc","group":"without_both","pathway_genes":["ABAT","ALDH5A1","APBA1","ARL6IP5","CASK","CHAT","CPLX1","DNAJC5","GAD1","GAD2","GLS","GLS2","HSPA8","LIN7A","LIN7B","LIN7C","MAOA","NAAA","PPFIA1","PPFIA2","PPFIA3","PPFIA4","RAB3A","RIMS1","SLC17A7","SLC18A2","SLC18A3","SLC1A1","SLC1A2","SLC1A3","SLC1A6","SLC1A7","SLC22A1","SLC22A2","SLC32A1","SLC38A2","SLC5A7","SLC6A1","SLC6A11","SLC6A12","SLC6A13","SNAP25","STX1A","STXBP1","SYN1","SYN2","SYN3","SYT1","TSPOAP1","UNC13B","VAMP2"],"cancer_rank":676.5,"pathway_times_enriched":5,"pathway_avg_rank":489.7,"mean_expr":-0.4545454545,"rank_size":0.0014781966,"avg_rank_size":0.0020420666,"avg_rank_label":"489.7"},{"pathway_name":"Neurotransmitter release cycle (R-HSA-112310)","Size":51,"Coverage":0.08,"TDP.bound":1.0,"TDP.estimate":1.0,"SC.adjP":0.0131054044,"Comp.0.99.adjP":0.0499734375,"cancer_type":"luad","group":"without_both","pathway_genes":["ABAT","ALDH5A1","APBA1","ARL6IP5","CASK","CHAT","CPLX1","DNAJC5","GAD1","GAD2","GLS","GLS2","HSPA8","LIN7A","LIN7B","LIN7C","MAOA","NAAA","PPFIA1","PPFIA2","PPFIA3","PPFIA4","RAB3A","RIMS1","SLC17A7","SLC18A2","SLC18A3","SLC1A1","SLC1A2","SLC1A3","SLC1A6","SLC1A7","SLC22A1","SLC22A2","SLC32A1","SLC38A2","SLC5A7","SLC6A1","SLC6A11","SLC6A12","SLC6A13","SNAP25","STX1A","STXBP1","SYN1","SYN2","SYN3","SYT1","TSPOAP1","UNC13B","VAMP2"],"cancer_rank":835.0,"pathway_times_enriched":5,"pathway_avg_rank":489.7,"mean_expr":-0.3333333333,"rank_size":0.0011976048,"avg_rank_size":0.0020420666,"avg_rank_label":"489.7"},{"pathway_name":"Neurotransmitter release cycle (R-HSA-112310)","Size":51,"Coverage":0.08,"TDP.bound":1.0,"TDP.estimate":1.0,"SC.adjP":0.0499147504,"Comp.0.99.adjP":0.0499147504,"cancer_type":"ovarian","group":"without_both","pathway_genes":["ABAT","ALDH5A1","APBA1","ARL6IP5","CASK","CHAT","CPLX1","DNAJC5","GAD1","GAD2","GLS","GLS2","HSPA8","LIN7A","LIN7B","LIN7C","MAOA","NAAA","PPFIA1","PPFIA2","PPFIA3","PPFIA4","RAB3A","RIMS1","SLC17A7","SLC18A2","SLC18A3","SLC1A1","SLC1A2","SLC1A3","SLC1A6","SLC1A7","SLC22A1","SLC22A2","SLC32A1","SLC38A2","SLC5A7","SLC6A1","SLC6A11","SLC6A12","SLC6A13","SNAP25","STX1A","STXBP1","SYN1","SYN2","SYN3","SYT1","TSPOAP1","UNC13B","VAMP2"],"cancer_rank":677.0,"pathway_times_enriched":5,"pathway_avg_rank":489.7,"mean_expr":-0.4285714286,"rank_size":0.0014771049,"avg_rank_size":0.0020420666,"avg_rank_label":"489.7"},{"pathway_name":"Interleukin-35 Signalling (R-HSA-8984722)","Size":12,"Coverage":0.08,"TDP.bound":1.0,"TDP.estimate":1.0,"SC.adjP":0.0498921085,"Comp.0.99.adjP":0.0498921085,"cancer_type":"colon","group":"without_both","pathway_genes":["CANX","EBI3","IL12A","IL12RB2","IL27RA","IL6ST","JAK1","JAK2","STAT1","STAT3","STAT4","TYK2"],"cancer_rank":881.0,"pathway_times_enriched":5,"pathway_avg_rank":492.0,"mean_expr":-0.2,"rank_size":0.0011350738,"avg_rank_size":0.0020325203,"avg_rank_label":"492.0"},{"pathway_name":"Interleukin-35 Signalling (R-HSA-8984722)","Size":12,"Coverage":0.17,"TDP.bound":1.0,"TDP.estimate":1.0,"SC.adjP":0.0000050332,"Comp.0.99.adjP":0.005568519,"cancer_type":"hnscc","group":"without_both","pathway_genes":["CANX","EBI3","IL12A","IL12RB2","IL27RA","IL6ST","JAK1","JAK2","STAT1","STAT3","STAT4","TYK2"],"cancer_rank":62.5,"pathway_times_enriched":5,"pathway_avg_rank":492.0,"mean_expr":0.6,"rank_size":0.016,"avg_rank_size":0.0020325203,"avg_rank_label":"492.0"},{"pathway_name":"Interleukin-35 Signalling (R-HSA-8984722)","Size":12,"Coverage":0.17,"TDP.bound":1.0,"TDP.estimate":1.0,"SC.adjP":0.0497956271,"Comp.0.99.adjP":0.0497956271,"cancer_type":"lscc","group":"without_both","pathway_genes":["CANX","EBI3","IL12A","IL12RB2","IL27RA","IL6ST","JAK1","JAK2","STAT1","STAT3","STAT4","TYK2"],"cancer_rank":676.5,"pathway_times_enriched":5,"pathway_avg_rank":492.0,"mean_expr":-0.1111111111,"rank_size":0.0014781966,"avg_rank_size":0.0020325203,"avg_rank_label":"492.0"},{"pathway_name":"Interleukin-35 Signalling (R-HSA-8984722)","Size":12,"Coverage":0.08,"TDP.bound":1.0,"TDP.estimate":1.0,"SC.adjP":0.0499734375,"Comp.0.99.adjP":0.0499734375,"cancer_type":"luad","group":"without_both","pathway_genes":["CANX","EBI3","IL12A","IL12RB2","IL27RA","IL6ST","JAK1","JAK2","STAT1","STAT3","STAT4","TYK2"],"cancer_rank":835.0,"pathway_times_enriched":5,"pathway_avg_rank":492.0,"mean_expr":-0.1111111111,"rank_size":0.0011976048,"avg_rank_size":0.0020325203,"avg_rank_label":"492.0"},{"pathway_name":"Interleukin-35 Signalling (R-HSA-8984722)","Size":12,"Coverage":0.08,"TDP.bound":1.0,"TDP.estimate":1.0,"SC.adjP":0.005724026,"Comp.0.99.adjP":0.005724026,"cancer_type":"ovarian","group":"without_both","pathway_genes":["CANX","EBI3","IL12A","IL12RB2","IL27RA","IL6ST","JAK1","JAK2","STAT1","STAT3","STAT4","TYK2"],"cancer_rank":5.0,"pathway_times_enriched":5,"pathway_avg_rank":492.0,"mean_expr":0.0,"rank_size":0.2,"avg_rank_size":0.0020325203,"avg_rank_label":"492.0"}]